pyany_serde-0.1.10.dist-info/METADATA
pyany_serde-0.1.10.dist-info/WHEEL
pyany_serde/pyany_serde_factory.py
pyany_serde/pyany_serde.pyi
pyany_serde/py.typed
pyany_serde/__init__.py
pyany_serde/python_serde.py
pyany_serde/pyany_serde.cpython-39-x86_64-linux-gnu.so
pyany_serde-0.1.10.dist-info/RECORD
