Metadata-Version: 2.4
Name: pyany-serde
Version: 0.1.10
Classifier: Programming Language :: Rust
Classifier: Programming Language :: Python :: Implementation :: CPython
Summary: Serialization and deserialization for Python objects
License: Apache-2.0
Requires-Python: >=3.8, <=3.12
